spArgValidatorPy/ArgValidator.py
spArgValidatorPy/__init__.py
spargvalidatorpy-1.0.7.dist-info/METADATA
spargvalidatorpy-1.0.7.dist-info/WHEEL
spargvalidatorpy-1.0.7.dist-info/licenses/LICENSE
spargvalidatorpy-1.0.7.dist-info/RECORD
