Metadata-Version: 2.4
Name: spArgValidatorPy
Version: 1.0.7
Summary: A Python package for validating function arguments and either raising an exception or returning the validated value.
Project-URL: Homepage, https://github.com/krokoreit/spArgValidatorPy
Project-URL: Source Code, https://github.com/krokoreit/spArgValidatorPy
Author-email: krokoreit <krokoreit@gmail.com>
License-Expression: MIT
License-File: LICENSE
Keywords: argument validation,function arguments,valid float,valid integer,valid string,validator
Classifier: Operating System :: OS Independent
Classifier: Programming Language :: Python :: 3
Requires-Python: >=3.10
